Workbook
Name NativeTimeline_Date: #N/A
Name Slicer_Brand: #N/A
Name Slicer_Country: #N/A

Sheet shoes_sales_dataset
A1: Sale_ID | B1: Date | C1: Brand | D1: Shoe_Type | E1: Color | F1: Country | G1: Sales_Channel | H1: Price_USD | I1: Units_Sold | J1: Revenue_USD | K1: Month | L1: High Value Sale | M1: Performance Category | N1: Growth | O1: Discount | P1: Adjust revenue
A2: S1 | B2: 45985 | C2: Nike | D2: Boots | E2: Blue | F2: UK | G2: Online | H2: 112.4 | I2: 4 | J2: 449.6 | K2: =TEXT(B2,"MMM") -> Nov | L2: =IF(J2>2000,"High","Low") -> Low | M2: =IF(J2>3000,"Excellent", IF(J2>1500,"Good", IF(J2>500,"Average","Low"))) -> Low | N2: 0 | O2: 0.5 | P2: =J2*(1-O2) -> 224.8
A3: S2 | B3: 45729 | C3: Skechers | D3: Boots | E3: Grey | F3: USA | G3: Mall | H3: 239.16 | I3: 4 | J3: 956.64 | K3: =TEXT(B3,"MMM") -> Mar | L3: =IF(J3>2000,"High","Low") -> Low | M3: =IF(J3>3000,"Excellent", IF(J3>1500,"Good", IF(J3>500,"Average","Low"))) -> Average | N3: =J3-J2 -> 507.04 | O3: 0.2 | P3: =J3*(1-O3) -> 765.312
A4: S3 | B4: 45874 | C4: Nike | D4: Running | E4: White | F4: UK | G4: Mall | H4: 191.04 | I4: 2 | J4: 382.08 | K4: =TEXT(B4,"MMM") -> Aug | L4: =IF(J4>2000,"High","Low") -> Low | M4: =IF(J4>3000,"Excellent", IF(J4>1500,"Good", IF(J4>500,"Average","Low"))) -> Low | N4: =J4-J3 -> -574.56 | O4: 0.1 | P4: =J4*(1-O4) -> 343.872
A5: S4 | B5: 45966 | C5: New Balance | D5: Casual | E5: Green | F5: UAE | G5: Mall | H5: 161.7 | I5: 1 | J5: 161.7 | K5: =TEXT(B5,"MMM") -> Nov | L5: =IF(J5>2000,"High","Low") -> Low | M5: =IF(J5>3000,"Excellent", IF(J5>1500,"Good", IF(J5>500,"Average","Low"))) -> Low | N5: =J5-J4 -> -220.38 | O5: 0.1 | P5: =J5*(1-O5) -> 145.53
A6: S5 | B6: 45937 | C6: Adidas | D6: Formal | E6: Grey | F6: France | G6: Online | H6: 64.32 | I6: 14 | J6: 900.48 | K6: =TEXT(B6,"MMM") -> Oct | L6: =IF(J6>2000,"High","Low") -> Low | M6: =IF(J6>3000,"Excellent", IF(J6>1500,"Good", IF(J6>500,"Average","Low"))) -> Average | N6: =J6-J5 -> 738.78 | O6: 0.1 | P6: =J6*(1-O6) -> 810.432
A7: S6 | B7: 45739 | C7: Puma | D7: Sports | E7: White | F7: UK | G7: Retail Store | H7: 64.32 | I7: 14 | J7: 900.48 | K7: =TEXT(B7,"MMM") -> Mar | L7: =IF(J7>2000,"High","Low") -> Low | M7: =IF(J7>3000,"Excellent", IF(J7>1500,"Good", IF(J7>500,"Average","Low"))) -> Average | N7: =J7-J6 -> 0 | O7: 0.1 | P7: =J7*(1-O7) -> 810.432
A8: S7 | B8: 45710 | C8: Reebok | D8: Running | E8: Blue | F8: Saudi Arabia | G8: Retail Store | H8: 42.78 | I8: 3 | J8: 128.34 | K8: =TEXT(B8,"MMM") -> Feb | L8: =IF(J8>2000,"High","Low") -> Low | M8: =IF(J8>3000,"Excellent", IF(J8>1500,"Good", IF(J8>500,"Average","Low"))) -> Low | N8: =J8-J7 -> -772.14 | O8: 0.1 | P8: =J8*(1-O8) -> 115.506
A9: S8 | B9: 45967 | C9: Nike | D9: Boots | E9: Red | F9: India | G9: Online | H9: 220.56 | I9: 9 | J9: 1985.04 | K9: =TEXT(B9,"MMM") -> Nov | L9: =IF(J9>2000,"High","Low") -> Low | M9: =IF(J9>3000,"Excellent", IF(J9>1500,"Good", IF(J9>500,"Average","Low"))) -> Good | N9: =J9-J8 -> 1856.7 | O9: 0.1 | P9: =J9*(1-O9) -> 1786.536
A10: S9 | B10: 45851 | C10: New Balance | D10: Sports | E10: Green | F10: India | G10: Retail Store | H10: 162.25 | I10: 3 | J10: 486.75 | K10: =TEXT(B10,"MMM") -> Jul | L10: =IF(J10>2000,"High","Low") -> Low | M10: =IF(J10>3000,"Excellent", IF(J10>1500,"Good", IF(J10>500,"Average","Low"))) -> Low | N10: =J10-J9 -> -1498.29 | O10: 0.1 | P10: =J10*(1-O10) -> 438.075
A11: S10 | B11: 45953 | C11: Skechers | D11: Running | E11: Black | F11: UAE | G11: Online | H11: 185.78 | I11: 7 | J11: 1300.46 | K11: =TEXT(B11,"MMM") -> Oct | L11: =IF(J11>2000,"High","Low") -> Low | M11: =IF(J11>3000,"Excellent", IF(J11>1500,"Good", IF(J11>500,"Average","Low"))) -> Average | N11: =J11-J10 -> 813.71 | O11: 0.1 | P11: =J11*(1-O11) -> 1170.414
A12: S11 | B12: 45806 | C12: Adidas | D12: Running | E12: Red | F12: France | G12: Retail Store | H12: 34.53 | I12: 3 | J12: 103.59 | K12: =TEXT(B12,"MMM") -> May | L12: =IF(J12>2000,"High","Low") -> Low | M12: =IF(J12>3000,"Excellent", IF(J12>1500,"Good", IF(J12>500,"Average","Low"))) -> Low | N12: =J12-J11 -> -1196.87 | O12: 0.1 | P12: =J12*(1-O12) -> 93.231
A13: S12 | B13: 45983 | C13: Adidas | D13: Sports | E13: Blue | F13: UK | G13: Mall | H13: 243.38 | I13: 12 | J13: 2920.56 | K13: =TEXT(B13,"MMM") -> Nov | L13: =IF(J13>2000,"High","Low") -> High | M13: =IF(J13>3000,"Excellent", IF(J13>1500,"Good", IF(J13>500,"Average","Low"))) -> Good | N13: =J13-J12 -> 2816.97 | O13: 0.1 | P13: =J13*(1-O13) -> 2628.504
A14: S13 | B14: 45794 | C14: New Balance | D14: Boots | E14: White | F14: India | G14: Mall | H14: 213.14 | I14: 3 | J14: 639.42 | K14: =TEXT(B14,"MMM") -> May | L14: =IF(J14>2000,"High","Low") -> Low | M14: =IF(J14>3000,"Excellent", IF(J14>1500,"Good", IF(J14>500,"Average","Low"))) -> Average | N14: =J14-J13 -> -2281.14 | O14: 0.1 | P14: =J14*(1-O14) -> 575.478
... A1001: S1000 | B1001: 45899 | C1001: Puma | D1001: Casual | E1001: Green | F1001: India | G1001: Online | H1001: 128.12 | I1001: 1 | J1001: 128.12 | K1001: =TEXT(B1001,"MMM") -> Aug | L1001: =IF(J1001>2000,"High","Low") -> Low | M1001: =IF(J1001>3000,"Excellent", IF(J1001>1500,"Good", IF(J1001>500,"Average","Low"))) -> Low | N1001: =J1001-J1000 -> -110.93 | O1001: 0.1 | P1001: =J1001*(1-O1001) -> 115.308
I1002: =SUBTOTAL(109,Table2[Units_Sold]) -> 10584 | J1002: =SUM(J2:J1001) -> 1453186 | P1002: =SUBTOTAL(109,Table2[Adjust revenue]) -> 1307591.9

Sheet Dashboard

Sheet Filter By Shoe Type
A2: Filter By Shoe Type
A3: Boots
AB4: Boots
AB5: Running
A6: Sale_ID | B6: Date | C6: Brand | D6: Shoe_Type | E6: Color | F6: Country | G6: Sales_Channel | H6: Price_USD | AB6: Casual
A7: {=IFERROR(_xlfn._xlws.FILTER(shoes_sales_dataset!A2:H1001,shoes_sales_dataset!D2:D1001=A3),"Select Shoe Type")} -> S1 | B7: 45985 | C7: Nike | D7: Boots | E7: Blue | F7: UK | G7: Online | H7: 112.4 | AB7: Formal
A8: S2 | B8: 45729 | C8: Skechers | D8: Boots | E8: Grey | F8: USA | G8: Mall | H8: 239.16 | AB8: Sports
A9: S8 | B9: 45967 | C9: Nike | D9: Boots | E9: Red | F9: India | G9: Online | H9: 220.56 | AB9: Sneakers
A10: S13 | B10: 45794 | C10: New Balance | D10: Boots | E10: White | F10: India | G10: Mall | H10: 213.14
A11: S35 | B11: 45770 | C11: Nike | D11: Boots | E11: Green | F11: USA | G11: Online | H11: 242.44
A12: S46 | B12: 45804 | C12: Skechers | D12: Boots | E12: Grey | F12: UAE | G12: Mall | H12: 175.75
A13: S52 | B13: 45975 | C13: Reebok | D13: Boots | E13: Grey | F13: India | G13: Mall | H13: 200.53
A14: S53 | B14: 45819 | C14: Adidas | D14: Boots | E14: Green | F14: France | G14: Online | H14: 236.69
A15: S54 | B15: 45793 | C15: Adidas | D15: Boots | E15: Green | F15: France | G15: Retail Store | H15: 226.86
A16: S58 | B16: 46018 | C16: New Balance | D16: Boots | E16: Grey | F16: USA | G16: Mall | H16: 73.12
A17: S61 | B17: 45833 | C17: Skechers | D17: Boots | E17: Blue | F17: India | G17: Retail Store | H17: 115.51
A18: S62 | B18: 45786 | C18: Nike | D18: Boots | E18: Red | F18: Saudi Arabia | G18: Retail Store | H18: 89.7
A19: S68 | B19: 45944 | C19: New Balance | D19: Boots | E19: White | F19: UK | G19: Online | H19: 206.48
A20: S72 | B20: 45774 | C20: Nike | D20: Boots | E20: White | F20: Germany | G20: Retail Store | H20: 73.72
A21: S77 | B21: 45755 | C21: Nike | D21: Boots | E21: Red | F21: USA | G21: Mall | H21: 199.68
... A182: S999 | B182: 45805 | C182: Puma | D182: Boots | E182: Black | F182: France | G182: Retail Store | H182: 239.05

Sheet Top 10 Customer
D7: Brand | E7: Shoe_Type | F7: Color | G7: Country | H7: Sales_Channel | I7: Price_USD | J7: Revenue_USD
C8: 1 | D8: =INDEX(shoes_sales_dataset!C2:C1001,MATCH(J8,shoes_sales_dataset!J2:J1001,0)) -> Skechers | E8: =INDEX(shoes_sales_dataset!D2:D1001,MATCH(J8,shoes_sales_dataset!J2:J1001,0)) -> Boots | F8: =INDEX(shoes_sales_dataset!E2:E1001,MATCH(J8,shoes_sales_dataset!J2:J1001,0)) -> Grey | G8: =INDEX(shoes_sales_dataset!F2:F1001,MATCH(J8,shoes_sales_dataset!J2:J1001,0)) -> Germany | H8: =INDEX(shoes_sales_dataset!G2:G1001,MATCH(J8,shoes_sales_dataset!J2:J1001,0)) -> Mall | I8: =INDEX(shoes_sales_dataset!H2:H1001,MATCH(J8,shoes_sales_dataset!J2:J1001,0)) -> 246.92 | J8: =LARGE(shoes_sales_dataset!J2:J1001,C8) -> 4938.4
C9: 2 | D9: =INDEX(shoes_sales_dataset!C3:C1002,MATCH(J9,shoes_sales_dataset!J3:J1002,0)) -> Skechers | E9: =INDEX(shoes_sales_dataset!D3:D1002,MATCH(J9,shoes_sales_dataset!J3:J1002,0)) -> Boots | F9: =INDEX(shoes_sales_dataset!E3:E1002,MATCH(J9,shoes_sales_dataset!J3:J1002,0)) -> Grey | G9: =INDEX(shoes_sales_dataset!F3:F1002,MATCH(J9,shoes_sales_dataset!J3:J1002,0)) -> Germany | H9: =INDEX(shoes_sales_dataset!G3:G1002,MATCH(J9,shoes_sales_dataset!J3:J1002,0)) -> Mall | I9: =INDEX(shoes_sales_dataset!H3:H1002,MATCH(J9,shoes_sales_dataset!J3:J1002,0)) -> 246.92 | J9: =LARGE(shoes_sales_dataset!J3:J1002,C9) -> 4938.4
C10: 3 | D10: =INDEX(shoes_sales_dataset!C4:C1003,MATCH(J10,shoes_sales_dataset!J4:J1003,0)) -> New Balance | E10: =INDEX(shoes_sales_dataset!D4:D1003,MATCH(J10,shoes_sales_dataset!J4:J1003,0)) -> Casual | F10: =INDEX(shoes_sales_dataset!E4:E1003,MATCH(J10,shoes_sales_dataset!J4:J1003,0)) -> Grey | G10: =INDEX(shoes_sales_dataset!F4:F1003,MATCH(J10,shoes_sales_dataset!J4:J1003,0)) -> Germany | H10: =INDEX(shoes_sales_dataset!G4:G1003,MATCH(J10,shoes_sales_dataset!J4:J1003,0)) -> Retail Store | I10: =INDEX(shoes_sales_dataset!H4:H1003,MATCH(J10,shoes_sales_dataset!J4:J1003,0)) -> 241.74 | J10: =LARGE(shoes_sales_dataset!J4:J1003,C10) -> 4834.8
C11: 4 | D11: =INDEX(shoes_sales_dataset!C5:C1004,MATCH(J11,shoes_sales_dataset!J5:J1004,0)) -> Nike | E11: =INDEX(shoes_sales_dataset!D5:D1004,MATCH(J11,shoes_sales_dataset!J5:J1004,0)) -> Sneakers | F11: =INDEX(shoes_sales_dataset!E5:E1004,MATCH(J11,shoes_sales_dataset!J5:J1004,0)) -> Grey | G11: =INDEX(shoes_sales_dataset!F5:F1004,MATCH(J11,shoes_sales_dataset!J5:J1004,0)) -> Saudi Arabia | H11: =INDEX(shoes_sales_dataset!G5:G1004,MATCH(J11,shoes_sales_dataset!J5:J1004,0)) -> Online | I11: =INDEX(shoes_sales_dataset!H5:H1004,MATCH(J11,shoes_sales_dataset!J5:J1004,0)) -> 241.44 | J11: =LARGE(shoes_sales_dataset!J5:J1004,C11) -> 4828.8
C12: 5 | D12: =INDEX(shoes_sales_dataset!C6:C1005,MATCH(J12,shoes_sales_dataset!J6:J1005,0)) -> Skechers | E12: =INDEX(shoes_sales_dataset!D6:D1005,MATCH(J12,shoes_sales_dataset!J6:J1005,0)) -> Boots | F12: =INDEX(shoes_sales_dataset!E6:E1005,MATCH(J12,shoes_sales_dataset!J6:J1005,0)) -> Grey | G12: =INDEX(shoes_sales_dataset!F6:F1005,MATCH(J12,shoes_sales_dataset!J6:J1005,0)) -> USA | H12: =INDEX(shoes_sales_dataset!G6:G1005,MATCH(J12,shoes_sales_dataset!J6:J1005,0)) -> Retail Store | I12: =INDEX(shoes_sales_dataset!H6:H1005,MATCH(J12,shoes_sales_dataset!J6:J1005,0)) -> 249.31 | J12: =LARGE(shoes_sales_dataset!J6:J1005,C12) -> 4736.89
C13: 6 | D13: =INDEX(shoes_sales_dataset!C7:C1006,MATCH(J13,shoes_sales_dataset!J7:J1006,0)) -> Skechers | E13: =INDEX(shoes_sales_dataset!D7:D1006,MATCH(J13,shoes_sales_dataset!J7:J1006,0)) -> Formal | F13: =INDEX(shoes_sales_dataset!E7:E1006,MATCH(J13,shoes_sales_dataset!J7:J1006,0)) -> Blue | G13: =INDEX(shoes_sales_dataset!F7:F1006,MATCH(J13,shoes_sales_dataset!J7:J1006,0)) -> Saudi Arabia | H13: =INDEX(shoes_sales_dataset!G7:G1006,MATCH(J13,shoes_sales_dataset!J7:J1006,0)) -> Online | I13: =INDEX(shoes_sales_dataset!H7:H1006,MATCH(J13,shoes_sales_dataset!J7:J1006,0)) -> 227.39 | J13: =LARGE(shoes_sales_dataset!J7:J1006,C13) -> 4547.8
C14: 7 | D14: =INDEX(shoes_sales_dataset!C8:C1007,MATCH(J14,shoes_sales_dataset!J8:J1007,0)) -> Adidas | E14: =INDEX(shoes_sales_dataset!D8:D1007,MATCH(J14,shoes_sales_dataset!J8:J1007,0)) -> Boots | F14: =INDEX(shoes_sales_dataset!E8:E1007,MATCH(J14,shoes_sales_dataset!J8:J1007,0)) -> Red | G14: =INDEX(shoes_sales_dataset!F8:F1007,MATCH(J14,shoes_sales_dataset!J8:J1007,0)) -> USA | H14: =INDEX(shoes_sales_dataset!G8:G1007,MATCH(J14,shoes_sales_dataset!J8:J1007,0)) -> Retail Store | I14: =INDEX(shoes_sales_dataset!H8:H1007,MATCH(J14,shoes_sales_dataset!J8:J1007,0)) -> 225.8 | J14: =LARGE(shoes_sales_dataset!J8:J1007,C14) -> 4516
C15: 8 | D15: =INDEX(shoes_sales_dataset!C9:C1008,MATCH(J15,shoes_sales_dataset!J9:J1008,0)) -> Nike | E15: =INDEX(shoes_sales_dataset!D9:D1008,MATCH(J15,shoes_sales_dataset!J9:J1008,0)) -> Sports | F15: =INDEX(shoes_sales_dataset!E9:E1008,MATCH(J15,shoes_sales_dataset!J9:J1008,0)) -> Red | G15: =INDEX(shoes_sales_dataset!F9:F1008,MATCH(J15,shoes_sales_dataset!J9:J1008,0)) -> Germany | H15: =INDEX(shoes_sales_dataset!G9:G1008,MATCH(J15,shoes_sales_dataset!J9:J1008,0)) -> Retail Store | I15: =INDEX(shoes_sales_dataset!H9:H1008,MATCH(J15,shoes_sales_dataset!J9:J1008,0)) -> 221.87 | J15: =LARGE(shoes_sales_dataset!J9:J1008,C15) -> 4437.4
C16: 9 | D16: =INDEX(shoes_sales_dataset!C10:C1009,MATCH(J16,shoes_sales_dataset!J10:J1009,0)) -> New Balance | E16: =INDEX(shoes_sales_dataset!D10:D1009,MATCH(J16,shoes_sales_dataset!J10:J1009,0)) -> Sneakers | F16: =INDEX(shoes_sales_dataset!E10:E1009,MATCH(J16,shoes_sales_dataset!J10:J1009,0)) -> White | G16: =INDEX(shoes_sales_dataset!F10:F1009,MATCH(J16,shoes_sales_dataset!J10:J1009,0)) -> Germany | H16: =INDEX(shoes_sales_dataset!G10:G1009,MATCH(J16,shoes_sales_dataset!J10:J1009,0)) -> Mall | I16: =INDEX(shoes_sales_dataset!H10:H1009,MATCH(J16,shoes_sales_dataset!J10:J1009,0)) -> 232.37 | J16: =LARGE(shoes_sales_dataset!J10:J1009,C16) -> 4415.03
C17: 10 | D17: =INDEX(shoes_sales_dataset!C11:C1010,MATCH(J17,shoes_sales_dataset!J11:J1010,0)) -> New Balance | E17: =INDEX(shoes_sales_dataset!D11:D1010,MATCH(J17,shoes_sales_dataset!J11:J1010,0)) -> Running | F17: =INDEX(shoes_sales_dataset!E11:E1010,MATCH(J17,shoes_sales_dataset!J11:J1010,0)) -> Grey | G17: =INDEX(shoes_sales_dataset!F11:F1010,MATCH(J17,shoes_sales_dataset!J11:J1010,0)) -> UAE | H17: =INDEX(shoes_sales_dataset!G11:G1010,MATCH(J17,shoes_sales_dataset!J11:J1010,0)) -> Online | I17: =INDEX(shoes_sales_dataset!H11:H1010,MATCH(J17,shoes_sales_dataset!J11:J1010,0)) -> 218.2 | J17: =LARGE(shoes_sales_dataset!J11:J1010,C17) -> 4364
C18: Grand Total | I18: =SUM(I8:I17) -> 2351.96 | J18: =SUM(J8:J17) -> 46557.52

Sheet Linear Regression
A1: SUMMARY OUTPUT
A3: Regression Statistics
A4: Multiple R | B4: 0.59102911
A5: R Square | B5: 0.34931541
A6: Adjusted R Square | B6: 0.34866342
A7: Standard Error | B7: 897.70782
A8: Observations | B8: 1000
A10: ANOVA
B11: df | C11: SS | D11: MS | E11: F | F11: Significance F
A12: Regression | B12: 1 | C12: 4.3176535e+08 | D12: 4.3176535e+08 | E12: 535.76923 | F12: 3.1749882e-95
A13: Residual | B13: 998 | C13: 8.0426758e+08 | D13: 805879.34
A14: Total | B14: 999 | C14: 1.2360329e+09
B16: Coefficients | C16: Standard Error | D16: t Stat | E16: P-value | F16: Lower 95% | G16: Upper 95% | H16: Lower 95.0% | I16: Upper 95.0%
A17: Intercept | B17: 43.055068 | C17: 67.210923 | D17: 0.64059629 | E17: 0.52193206 | F17: -88.835873 | G17: 174.94601 | H17: -88.835873 | I17: 174.94601
A18: X Variable 1 | B18: 10.228983 | C18: 0.44191991 | D18: 23.146689 | E18: 3.1749882e-95 | F18: 9.3617841 | G18: 11.096182 | H18: 9.3617841 | I18: 11.096182

Sheet Revenue by Brand
A3: Row Labels | B3: Sum of Revenue_USD
A4: Adidas | B4: 83487.16
A5: New Balance | B5: 64032.37
A6: Nike | B6: 58210.93
A7: Puma | B7: 59793.19
A8: Reebok | B8: 74125.25
A9: Skechers | B9: 86791.26
A10: Grand Total | B10: 426440.16

Sheet Monthly Sales
A3: Row Labels | B3: Sum of Revenue_USD
A4: Jan | B4: 102989.92
A5: Feb | B5: 128479.05
A6: Mar | B6: 117157.86
A7: Apr | B7: 115753.37
A8: May | B8: 125637.78
A9: Jun | B9: 126802.88
A10: Jul | B10: 140198.13
A11: Aug | B11: 96240.75
A12: Sep | B12: 95768.73
A13: Oct | B13: 146726.46
A14: Nov | B14: 131542.53
A15: Dec | B15: 125888.57
A16: Grand Total | B16: 1453186

Sheet Sales Channel Share
A3: Row Labels | B3: Sum of Revenue_USD
A4: Mall | B4: 479288.58
A5: Online | B5: 467772.32
A6: Retail Store | B6: 506125.13
A7: Grand Total | B7: 1453186

Sheet Revenue by Country
A1: Row Labels | B1: Sum of Revenue_USD
A2: France | B2: 228079.04
A3: Germany | B3: 199667.31
A4: India | B4: 177959.76
A5: Saudi Arabia | B5: 190489.82
A6: UAE | B6: 239807.55
A7: UK | B7: 186632.61
A8: USA | B8: 230549.94
A9: Grand Total | B9: 1453186

Sheet Price and Reavenue by Country
A3: Row Labels | B3: Sum of Price_USD | C3: Sum of Revenue_USD
A4: France | B4: 21934.4 | C4: 228079.04
A5: Germany | B5: 17637.67 | C5: 199667.31
A6: India | B6: 20025.55 | C6: 177959.76
A7: Saudi Arabia | B7: 17032.27 | C7: 190489.82
A8: UAE | B8: 22485.55 | C8: 239807.55
A9: UK | B9: 17801.23 | C9: 186632.61
A10: USA | B10: 20939.75 | C10: 230549.94
A11: Grand Total | B11: 137856.42 | C11: 1453186

Sheet Sum Revenue & Sum Adjust Revenu
A3: Row Labels | B3: Sum of Adjust revenue | C3: Sum of Revenue_USD
A4: Adidas | B4: 231335.14 | C4: 257039.04
A5: New Balance | B5: 235468.51 | C5: 261631.68
A6: Nike | B6: 173313.3 | C6: 192770.15
A7: Puma | B7: 210374.63 | C7: 233749.59
A8: Reebok | B8: 214944.25 | C8: 238826.94
A9: Skechers | B9: 242156.1 | C9: 269168.63
A10: Grand Total | B10: 1307591.9 | C10: 1453186
